Flastel/__init__.py
Flastel/methods.py
Flastel/func/__init__.py
Flastel/func/more_class.py
Flastel/func/polling_func.py
Flastel/func/webhook_func.py
Flastel-0.0.14.5.post1.dist-info/LICENSE
Flastel-0.0.14.5.post1.dist-info/METADATA
Flastel-0.0.14.5.post1.dist-info/WHEEL
Flastel-0.0.14.5.post1.dist-info/top_level.txt
Flastel-0.0.14.5.post1.dist-info/RECORD
