Metadata-Version: 2.1
Name: Flastel
Version: 0.0.14.5.post1
Summary: Flastel – Telegram Bot API.
Home-page: https://github.com/DepyXa/Flastel
Author: DepyXa
Author-email: dere96632@gmail.com
Project-URL: GitHub, https://github.com/DepyXa
Keywords: Telegram Bot API
Requires-Python: >=3.6
License-File: LICENSE
Requires-Dist: requests >=2.25.1
Requires-Dist: aiohttp >=3.8.6
